package in.gov.hp.Aadhaar_HP.SRDH;

import android.content.Context;
import android.os.AsyncTask;
import android.widget.ProgressBar;
import android.widget.Toast;
import java.util.List;

class b
  extends AsyncTask
{
  String a = null;
  
  b(AdvancedListFive paramAdvancedListFive) {}
  
  /* Error */
  protected String a(String... paramVarArgs)
  {
    // Byte code:
    //   0: aload_0
    //   1: getfield 10	in/gov/hp/Aadhaar_HP/SRDH/b:b	Lin/gov/hp/Aadhaar_HP/SRDH/AdvancedListFive;
    //   4: astore_2
    //   5: new 18	java/net/URL
    //   8: astore_3
    //   9: ldc 20
    //   11: astore 4
    //   13: aload_3
    //   14: aload 4
    //   16: invokespecial 23	java/net/URL:<init>	(Ljava/lang/String;)V
    //   19: aload_2
    //   20: aload_3
    //   21: putfield 29	in/gov/hp/Aadhaar_HP/SRDH/AdvancedListFive:i	Ljava/net/URL;
    //   24: aload_0
    //   25: getfield 10	in/gov/hp/Aadhaar_HP/SRDH/b:b	Lin/gov/hp/Aadhaar_HP/SRDH/AdvancedListFive;
    //   28: astore_3
    //   29: aload_0
    //   30: getfield 10	in/gov/hp/Aadhaar_HP/SRDH/b:b	Lin/gov/hp/Aadhaar_HP/SRDH/AdvancedListFive;
    //   33: astore_2
    //   34: aload_2
    //   35: getfield 29	in/gov/hp/Aadhaar_HP/SRDH/AdvancedListFive:i	Ljava/net/URL;
    //   38: astore_2
    //   39: aload_2
    //   40: invokevirtual 33	java/net/URL:openConnection	()Ljava/net/URLConnection;
    //   43: astore_2
    //   44: aload_2
    //   45: checkcast 35	java/net/HttpURLConnection
    //   48: astore_2
    //   49: aload_3
    //   50: aload_2
    //   51: putfield 39	in/gov/hp/Aadhaar_HP/SRDH/AdvancedListFive:j	Ljava/net/HttpURLConnection;
    //   54: aload_0
    //   55: getfield 10	in/gov/hp/Aadhaar_HP/SRDH/b:b	Lin/gov/hp/Aadhaar_HP/SRDH/AdvancedListFive;
    //   58: astore_2
    //   59: aload_2
    //   60: getfield 39	in/gov/hp/Aadhaar_HP/SRDH/AdvancedListFive:j	Ljava/net/HttpURLConnection;
    //   63: astore_2
    //   64: iconst_1
    //   65: istore 5
    //   67: aload_2
    //   68: iload 5
    //   70: invokevirtual 44	java/net/HttpURLConnection:setDoOutput	(Z)V
    //   73: aload_0
    //   74: getfield 10	in/gov/hp/Aadhaar_HP/SRDH/b:b	Lin/gov/hp/Aadhaar_HP/SRDH/AdvancedListFive;
    //   77: astore_2
    //   78: aload_2
    //   79: getfield 39	in/gov/hp/Aadhaar_HP/SRDH/AdvancedListFive:j	Ljava/net/HttpURLConnection;
    //   82: astore_2
    //   83: ldc 46
    //   85: astore_3
    //   86: aload_2
    //   87: aload_3
    //   88: invokevirtual 49	java/net/HttpURLConnection:setRequestMethod	(Ljava/lang/String;)V
    //   91: aload_0
    //   92: getfield 10	in/gov/hp/Aadhaar_HP/SRDH/b:b	Lin/gov/hp/Aadhaar_HP/SRDH/AdvancedListFive;
    //   95: astore_2
    //   96: aload_2
    //   97: getfield 39	in/gov/hp/Aadhaar_HP/SRDH/AdvancedListFive:j	Ljava/net/HttpURLConnection;
    //   100: astore_2
    //   101: iconst_0
    //   102: istore 5
    //   104: aconst_null
    //   105: astore_3
    //   106: aload_2
    //   107: iconst_0
    //   108: invokevirtual 52	java/net/HttpURLConnection:setUseCaches	(Z)V
    //   111: aload_0
    //   112: getfield 10	in/gov/hp/Aadhaar_HP/SRDH/b:b	Lin/gov/hp/Aadhaar_HP/SRDH/AdvancedListFive;
    //   115: astore_2
    //   116: aload_2
    //   117: getfield 39	in/gov/hp/Aadhaar_HP/SRDH/AdvancedListFive:j	Ljava/net/HttpURLConnection;
    //   120: astore_2
    //   121: sipush 20000
    //   124: istore 5
    //   126: aload_2
    //   127: iload 5
    //   129: invokevirtual 57	java/net/HttpURLConnection:setConnectTimeout	(I)V
    //   132: aload_0
    //   133: getfield 10	in/gov/hp/Aadhaar_HP/SRDH/b:b	Lin/gov/hp/Aadhaar_HP/SRDH/AdvancedListFive;
    //   136: astore_2
    //   137: aload_2
    //   138: getfield 39	in/gov/hp/Aadhaar_HP/SRDH/AdvancedListFive:j	Ljava/net/HttpURLConnection;
    //   141: astore_2
    //   142: sipush 20000
    //   145: istore 5
    //   147: aload_2
    //   148: iload 5
    //   150: invokevirtual 60	java/net/HttpURLConnection:setReadTimeout	(I)V
    //   153: aload_0
    //   154: getfield 10	in/gov/hp/Aadhaar_HP/SRDH/b:b	Lin/gov/hp/Aadhaar_HP/SRDH/AdvancedListFive;
    //   157: astore_2
    //   158: aload_2
    //   159: getfield 39	in/gov/hp/Aadhaar_HP/SRDH/AdvancedListFive:j	Ljava/net/HttpURLConnection;
    //   162: astore_2
    //   163: ldc 62
    //   165: astore_3
    //   166: ldc 64
    //   168: astore 4
    //   170: aload_2
    //   171: aload_3
    //   172: aload 4
    //   174: invokevirtual 68	java/net/HttpURLConnection:setRequestProperty	(Ljava/lang/String;Ljava/lang/String;)V
    //   177: aload_0
    //   178: getfield 10	in/gov/hp/Aadhaar_HP/SRDH/b:b	Lin/gov/hp/Aadhaar_HP/SRDH/AdvancedListFive;
    //   181: astore_2
    //   182: aload_2
    //   183: getfield 39	in/gov/hp/Aadhaar_HP/SRDH/AdvancedListFive:j	Ljava/net/HttpURLConnection;
    //   186: astore_2
    //   187: aload_2
    //   188: invokevirtual 71	java/net/HttpURLConnection:connect	()V
    //   191: new 73	org/json/JSONStringer
    //   194: astore_2
    //   195: aload_2
    //   196: invokespecial 74	org/json/JSONStringer:<init>	()V
    //   199: aload_2
    //   200: invokevirtual 78	org/json/JSONStringer:object	()Lorg/json/JSONStringer;
    //   203: astore_2
    //   204: ldc 80
    //   206: astore_3
    //   207: aload_2
    //   208: aload_3
    //   209: invokevirtual 84	org/json/JSONStringer:key	(Ljava/lang/String;)Lorg/json/JSONStringer;
    //   212: astore_2
    //   213: aload_2
    //   214: invokevirtual 78	org/json/JSONStringer:object	()Lorg/json/JSONStringer;
    //   217: astore_2
    //   218: ldc 86
    //   220: astore_3
    //   221: aload_2
    //   222: aload_3
    //   223: invokevirtual 84	org/json/JSONStringer:key	(Ljava/lang/String;)Lorg/json/JSONStringer;
    //   226: astore_2
    //   227: iconst_0
    //   228: istore 5
    //   230: aconst_null
    //   231: astore_3
    //   232: aload_1
    //   233: iconst_0
    //   234: aaload
    //   235: astore_3
    //   236: aload_2
    //   237: aload_3
    //   238: invokevirtual 90	org/json/JSONStringer:value	(Ljava/lang/Object;)Lorg/json/JSONStringer;
    //   241: astore_2
    //   242: ldc 92
    //   244: astore_3
    //   245: aload_2
    //   246: aload_3
    //   247: invokevirtual 84	org/json/JSONStringer:key	(Ljava/lang/String;)Lorg/json/JSONStringer;
    //   250: astore_2
    //   251: iconst_1
    //   252: istore 5
    //   254: aload_1
    //   255: iload 5
    //   257: aaload
    //   258: astore_3
    //   259: aload_2
    //   260: aload_3
    //   261: invokevirtual 90	org/json/JSONStringer:value	(Ljava/lang/Object;)Lorg/json/JSONStringer;
    //   264: astore_2
    //   265: ldc 94
    //   267: astore_3
    //   268: aload_2
    //   269: aload_3
    //   270: invokevirtual 84	org/json/JSONStringer:key	(Ljava/lang/String;)Lorg/json/JSONStringer;
    //   273: astore_2
    //   274: iconst_2
    //   275: istore 5
    //   277: aload_1
    //   278: iload 5
    //   280: aaload
    //   281: astore_3
    //   282: aload_2
    //   283: aload_3
    //   284: invokevirtual 90	org/json/JSONStringer:value	(Ljava/lang/Object;)Lorg/json/JSONStringer;
    //   287: astore_2
    //   288: ldc 97
    //   290: astore_3
    //   291: aload_2
    //   292: aload_3
    //   293: invokevirtual 84	org/json/JSONStringer:key	(Ljava/lang/String;)Lorg/json/JSONStringer;
    //   296: astore_2
    //   297: iconst_3
    //   298: istore 5
    //   300: aload_1
    //   301: iload 5
    //   303: aaload
    //   304: astore_3
    //   305: aload_2
    //   306: aload_3
    //   307: invokevirtual 90	org/json/JSONStringer:value	(Ljava/lang/Object;)Lorg/json/JSONStringer;
    //   310: astore_2
    //   311: ldc 100
    //   313: astore_3
    //   314: aload_2
    //   315: aload_3
    //   316: invokevirtual 84	org/json/JSONStringer:key	(Ljava/lang/String;)Lorg/json/JSONStringer;
    //   319: astore_2
    //   320: iconst_4
    //   321: istore 5
    //   323: aload_1
    //   324: iload 5
    //   326: aaload
    //   327: astore_3
    //   328: aload_2
    //   329: aload_3
    //   330: invokevirtual 90	org/json/JSONStringer:value	(Ljava/lang/Object;)Lorg/json/JSONStringer;
    //   333: astore_2
    //   334: aload_2
    //   335: invokevirtual 104	org/json/JSONStringer:endObject	()Lorg/json/JSONStringer;
    //   338: astore_2
    //   339: aload_2
    //   340: invokevirtual 104	org/json/JSONStringer:endObject	()Lorg/json/JSONStringer;
    //   343: astore_2
    //   344: getstatic 110	java/lang/System:out	Ljava/io/PrintStream;
    //   347: astore_3
    //   348: new 112	java/lang/StringBuilder
    //   351: astore 4
    //   353: aload 4
    //   355: invokespecial 113	java/lang/StringBuilder:<init>	()V
    //   358: ldc 115
    //   360: astore 6
    //   362: aload 4
    //   364: aload 6
    //   366: invokevirtual 119	java/lang/StringBuilder:append	(Ljava/lang/String;)Ljava/lang/StringBuilder;
    //   369: astore 4
    //   371: aload_2
    //   372: invokevirtual 123	org/json/JSONStringer:toString	()Ljava/lang/String;
    //   375: astore 6
    //   377: aload 4
    //   379: aload 6
    //   381: invokevirtual 119	java/lang/StringBuilder:append	(Ljava/lang/String;)Ljava/lang/StringBuilder;
    //   384: astore 4
    //   386: aload 4
    //   388: invokevirtual 124	java/lang/StringBuilder:toString	()Ljava/lang/String;
    //   391: astore 4
    //   393: aload_3
    //   394: aload 4
    //   396: invokevirtual 129	java/io/PrintStream:println	(Ljava/lang/String;)V
    //   399: new 131	java/io/OutputStreamWriter
    //   402: astore_3
    //   403: aload_0
    //   404: getfield 10	in/gov/hp/Aadhaar_HP/SRDH/b:b	Lin/gov/hp/Aadhaar_HP/SRDH/AdvancedListFive;
    //   407: astore 4
    //   409: aload 4
    //   411: getfield 39	in/gov/hp/Aadhaar_HP/SRDH/AdvancedListFive:j	Ljava/net/HttpURLConnection;
    //   414: astore 4
    //   416: aload 4
    //   418: invokevirtual 135	java/net/HttpURLConnection:getOutputStream	()Ljava/io/OutputStream;
    //   421: astore 4
    //   423: aload_3
    //   424: aload 4
    //   426: invokespecial 138	java/io/OutputStreamWriter:<init>	(Ljava/io/OutputStream;)V
    //   429: aload_2
    //   430: invokevirtual 123	org/json/JSONStringer:toString	()Ljava/lang/String;
    //   433: astore_2
    //   434: aload_3
    //   435: aload_2
    //   436: invokevirtual 141	java/io/OutputStreamWriter:write	(Ljava/lang/String;)V
    //   439: aload_3
    //   440: invokevirtual 144	java/io/OutputStreamWriter:close	()V
    //   443: aload_0
    //   444: getfield 10	in/gov/hp/Aadhaar_HP/SRDH/b:b	Lin/gov/hp/Aadhaar_HP/SRDH/AdvancedListFive;
    //   447: astore_2
    //   448: aload_2
    //   449: getfield 39	in/gov/hp/Aadhaar_HP/SRDH/AdvancedListFive:j	Ljava/net/HttpURLConnection;
    //   452: astore_2
    //   453: aload_2
    //   454: invokevirtual 148	java/net/HttpURLConnection:getResponseCode	()I
    //   457: istore 7
    //   459: sipush 200
    //   462: istore 5
    //   464: iload 7
    //   466: iload 5
    //   468: if_icmpne +296 -> 764
    //   471: getstatic 110	java/lang/System:out	Ljava/io/PrintStream;
    //   474: astore_3
    //   475: new 112	java/lang/StringBuilder
    //   478: astore 4
    //   480: aload 4
    //   482: invokespecial 113	java/lang/StringBuilder:<init>	()V
    //   485: aload 4
    //   487: iload 7
    //   489: invokevirtual 152	java/lang/StringBuilder:append	(I)Ljava/lang/StringBuilder;
    //   492: astore_2
    //   493: ldc -102
    //   495: astore 4
    //   497: aload_2
    //   498: aload 4
    //   500: invokevirtual 119	java/lang/StringBuilder:append	(Ljava/lang/String;)Ljava/lang/StringBuilder;
    //   503: astore_2
    //   504: aload_2
    //   505: invokevirtual 124	java/lang/StringBuilder:toString	()Ljava/lang/String;
    //   508: astore_2
    //   509: aload_3
    //   510: aload_2
    //   511: invokevirtual 129	java/io/PrintStream:println	(Ljava/lang/String;)V
    //   514: new 156	java/io/BufferedReader
    //   517: astore_2
    //   518: new 158	java/io/InputStreamReader
    //   521: astore_3
    //   522: aload_0
    //   523: getfield 10	in/gov/hp/Aadhaar_HP/SRDH/b:b	Lin/gov/hp/Aadhaar_HP/SRDH/AdvancedListFive;
    //   526: astore 4
    //   528: aload 4
    //   530: getfield 39	in/gov/hp/Aadhaar_HP/SRDH/AdvancedListFive:j	Ljava/net/HttpURLConnection;
    //   533: astore 4
    //   535: aload 4
    //   537: invokevirtual 162	java/net/HttpURLConnection:getInputStream	()Ljava/io/InputStream;
    //   540: astore 4
    //   542: ldc -92
    //   544: astore 6
    //   546: aload_3
    //   547: aload 4
    //   549: aload 6
    //   551: invokespecial 167	java/io/InputStreamReader:<init>	(Ljava/io/InputStream;Ljava/lang/String;)V
    //   554: aload_2
    //   555: aload_3
    //   556: invokespecial 170	java/io/BufferedReader:<init>	(Ljava/io/Reader;)V
    //   559: aload_2
    //   560: invokevirtual 173	java/io/BufferedReader:readLine	()Ljava/lang/String;
    //   563: astore_3
    //   564: aload_3
    //   565: ifnull +168 -> 733
    //   568: aload_0
    //   569: getfield 10	in/gov/hp/Aadhaar_HP/SRDH/b:b	Lin/gov/hp/Aadhaar_HP/SRDH/AdvancedListFive;
    //   572: astore 4
    //   574: aload 4
    //   576: getfield 177	in/gov/hp/Aadhaar_HP/SRDH/AdvancedListFive:k	Ljava/lang/StringBuilder;
    //   579: astore 4
    //   581: new 112	java/lang/StringBuilder
    //   584: astore 6
    //   586: aload 6
    //   588: invokespecial 113	java/lang/StringBuilder:<init>	()V
    //   591: aload 6
    //   593: aload_3
    //   594: invokevirtual 119	java/lang/StringBuilder:append	(Ljava/lang/String;)Ljava/lang/StringBuilder;
    //   597: astore_3
    //   598: ldc -77
    //   600: astore 6
    //   602: aload_3
    //   603: aload 6
    //   605: invokevirtual 119	java/lang/StringBuilder:append	(Ljava/lang/String;)Ljava/lang/StringBuilder;
    //   608: astore_3
    //   609: aload_3
    //   610: invokevirtual 124	java/lang/StringBuilder:toString	()Ljava/lang/String;
    //   613: astore_3
    //   614: aload 4
    //   616: aload_3
    //   617: invokevirtual 119	java/lang/StringBuilder:append	(Ljava/lang/String;)Ljava/lang/StringBuilder;
    //   620: pop
    //   621: getstatic 110	java/lang/System:out	Ljava/io/PrintStream;
    //   624: astore_3
    //   625: new 112	java/lang/StringBuilder
    //   628: astore 4
    //   630: aload 4
    //   632: invokespecial 113	java/lang/StringBuilder:<init>	()V
    //   635: aload_0
    //   636: getfield 10	in/gov/hp/Aadhaar_HP/SRDH/b:b	Lin/gov/hp/Aadhaar_HP/SRDH/AdvancedListFive;
    //   639: astore 6
    //   641: aload 6
    //   643: getfield 177	in/gov/hp/Aadhaar_HP/SRDH/AdvancedListFive:k	Ljava/lang/StringBuilder;
    //   646: astore 6
    //   648: aload 6
    //   650: invokevirtual 124	java/lang/StringBuilder:toString	()Ljava/lang/String;
    //   653: astore 6
    //   655: aload 4
    //   657: aload 6
    //   659: invokevirtual 119	java/lang/StringBuilder:append	(Ljava/lang/String;)Ljava/lang/StringBuilder;
    //   662: astore 4
    //   664: ldc -102
    //   666: astore 6
    //   668: aload 4
    //   670: aload 6
    //   672: invokevirtual 119	java/lang/StringBuilder:append	(Ljava/lang/String;)Ljava/lang/StringBuilder;
    //   675: astore 4
    //   677: aload 4
    //   679: invokevirtual 124	java/lang/StringBuilder:toString	()Ljava/lang/String;
    //   682: astore 4
    //   684: aload_3
    //   685: aload 4
    //   687: invokevirtual 129	java/io/PrintStream:println	(Ljava/lang/String;)V
    //   690: goto -131 -> 559
    //   693: astore_2
    //   694: aload_2
    //   695: invokevirtual 184	java/net/MalformedURLException:printStackTrace	()V
    //   698: aload_0
    //   699: getfield 10	in/gov/hp/Aadhaar_HP/SRDH/b:b	Lin/gov/hp/Aadhaar_HP/SRDH/AdvancedListFive;
    //   702: getfield 39	in/gov/hp/Aadhaar_HP/SRDH/AdvancedListFive:j	Ljava/net/HttpURLConnection;
    //   705: astore_2
    //   706: aload_2
    //   707: ifnull +15 -> 722
    //   710: aload_0
    //   711: getfield 10	in/gov/hp/Aadhaar_HP/SRDH/b:b	Lin/gov/hp/Aadhaar_HP/SRDH/AdvancedListFive;
    //   714: getfield 39	in/gov/hp/Aadhaar_HP/SRDH/AdvancedListFive:j	Ljava/net/HttpURLConnection;
    //   717: astore_2
    //   718: aload_2
    //   719: invokevirtual 187	java/net/HttpURLConnection:disconnect	()V
    //   722: aload_0
    //   723: getfield 10	in/gov/hp/Aadhaar_HP/SRDH/b:b	Lin/gov/hp/Aadhaar_HP/SRDH/AdvancedListFive;
    //   726: getfield 177	in/gov/hp/Aadhaar_HP/SRDH/AdvancedListFive:k	Ljava/lang/StringBuilder;
    //   729: invokevirtual 124	java/lang/StringBuilder:toString	()Ljava/lang/String;
    //   732: areturn
    //   733: aload_2
    //   734: invokevirtual 188	java/io/BufferedReader:close	()V
    //   737: aload_0
    //   738: getfield 10	in/gov/hp/Aadhaar_HP/SRDH/b:b	Lin/gov/hp/Aadhaar_HP/SRDH/AdvancedListFive;
    //   741: getfield 39	in/gov/hp/Aadhaar_HP/SRDH/AdvancedListFive:j	Ljava/net/HttpURLConnection;
    //   744: astore_2
    //   745: aload_2
    //   746: ifnull -24 -> 722
    //   749: aload_0
    //   750: getfield 10	in/gov/hp/Aadhaar_HP/SRDH/b:b	Lin/gov/hp/Aadhaar_HP/SRDH/AdvancedListFive;
    //   753: getfield 39	in/gov/hp/Aadhaar_HP/SRDH/AdvancedListFive:j	Ljava/net/HttpURLConnection;
    //   756: astore_2
    //   757: aload_2
    //   758: invokevirtual 187	java/net/HttpURLConnection:disconnect	()V
    //   761: goto -39 -> 722
    //   764: getstatic 110	java/lang/System:out	Ljava/io/PrintStream;
    //   767: astore_2
    //   768: aload_0
    //   769: getfield 10	in/gov/hp/Aadhaar_HP/SRDH/b:b	Lin/gov/hp/Aadhaar_HP/SRDH/AdvancedListFive;
    //   772: astore_3
    //   773: aload_3
    //   774: getfield 39	in/gov/hp/Aadhaar_HP/SRDH/AdvancedListFive:j	Ljava/net/HttpURLConnection;
    //   777: astore_3
    //   778: aload_3
    //   779: invokevirtual 191	java/net/HttpURLConnection:getResponseMessage	()Ljava/lang/String;
    //   782: astore_3
    //   783: aload_2
    //   784: aload_3
    //   785: invokevirtual 129	java/io/PrintStream:println	(Ljava/lang/String;)V
    //   788: goto -51 -> 737
    //   791: astore_2
    //   792: aload_2
    //   793: invokevirtual 194	java/io/IOException:printStackTrace	()V
    //   796: aload_0
    //   797: getfield 10	in/gov/hp/Aadhaar_HP/SRDH/b:b	Lin/gov/hp/Aadhaar_HP/SRDH/AdvancedListFive;
    //   800: getfield 39	in/gov/hp/Aadhaar_HP/SRDH/AdvancedListFive:j	Ljava/net/HttpURLConnection;
    //   803: astore_2
    //   804: aload_2
    //   805: ifnull -83 -> 722
    //   808: aload_0
    //   809: getfield 10	in/gov/hp/Aadhaar_HP/SRDH/b:b	Lin/gov/hp/Aadhaar_HP/SRDH/AdvancedListFive;
    //   812: getfield 39	in/gov/hp/Aadhaar_HP/SRDH/AdvancedListFive:j	Ljava/net/HttpURLConnection;
    //   815: astore_2
    //   816: aload_2
    //   817: invokevirtual 187	java/net/HttpURLConnection:disconnect	()V
    //   820: goto -98 -> 722
    //   823: astore_2
    //   824: aload_2
    //   825: invokevirtual 197	org/json/JSONException:printStackTrace	()V
    //   828: aload_0
    //   829: getfield 10	in/gov/hp/Aadhaar_HP/SRDH/b:b	Lin/gov/hp/Aadhaar_HP/SRDH/AdvancedListFive;
    //   832: getfield 39	in/gov/hp/Aadhaar_HP/SRDH/AdvancedListFive:j	Ljava/net/HttpURLConnection;
    //   835: astore_2
    //   836: aload_2
    //   837: ifnull -115 -> 722
    //   840: aload_0
    //   841: getfield 10	in/gov/hp/Aadhaar_HP/SRDH/b:b	Lin/gov/hp/Aadhaar_HP/SRDH/AdvancedListFive;
    //   844: getfield 39	in/gov/hp/Aadhaar_HP/SRDH/AdvancedListFive:j	Ljava/net/HttpURLConnection;
    //   847: astore_2
    //   848: aload_2
    //   849: invokevirtual 187	java/net/HttpURLConnection:disconnect	()V
    //   852: goto -130 -> 722
    //   855: astore_2
    //   856: aload_0
    //   857: getfield 10	in/gov/hp/Aadhaar_HP/SRDH/b:b	Lin/gov/hp/Aadhaar_HP/SRDH/AdvancedListFive;
    //   860: getfield 39	in/gov/hp/Aadhaar_HP/SRDH/AdvancedListFive:j	Ljava/net/HttpURLConnection;
    //   863: astore_3
    //   864: aload_3
    //   865: ifnull +15 -> 880
    //   868: aload_0
    //   869: getfield 10	in/gov/hp/Aadhaar_HP/SRDH/b:b	Lin/gov/hp/Aadhaar_HP/SRDH/AdvancedListFive;
    //   872: getfield 39	in/gov/hp/Aadhaar_HP/SRDH/AdvancedListFive:j	Ljava/net/HttpURLConnection;
    //   875: astore_3
    //   876: aload_3
    //   877: invokevirtual 187	java/net/HttpURLConnection:disconnect	()V
    //   880: aload_2
    //   881: athrow
    // Local variable table:
    //   start	length	slot	name	signature
    //   0	882	0	this	b
    //   0	882	1	paramVarArgs	String[]
    //   4	556	2	localObject1	Object
    //   693	2	2	localMalformedURLException	java.net.MalformedURLException
    //   705	79	2	localObject2	Object
    //   791	2	2	localIOException	java.io.IOException
    //   803	14	2	localHttpURLConnection1	java.net.HttpURLConnection
    //   823	2	2	localJSONException	org.json.JSONException
    //   835	14	2	localHttpURLConnection2	java.net.HttpURLConnection
    //   855	26	2	localObject3	Object
    //   8	869	3	localObject4	Object
    //   11	675	4	localObject5	Object
    //   65	38	5	bool	boolean
    //   124	345	5	i	int
    //   360	311	6	localObject6	Object
    //   457	31	7	j	int
    // Exception table:
    //   from	to	target	type
    //   0	4	693	java/net/MalformedURLException
    //   5	8	693	java/net/MalformedURLException
    //   14	19	693	java/net/MalformedURLException
    //   20	24	693	java/net/MalformedURLException
    //   24	28	693	java/net/MalformedURLException
    //   29	33	693	java/net/MalformedURLException
    //   34	38	693	java/net/MalformedURLException
    //   39	43	693	java/net/MalformedURLException
    //   44	48	693	java/net/MalformedURLException
    //   50	54	693	java/net/MalformedURLException
    //   54	58	693	java/net/MalformedURLException
    //   59	63	693	java/net/MalformedURLException
    //   68	73	693	java/net/MalformedURLException
    //   73	77	693	java/net/MalformedURLException
    //   78	82	693	java/net/MalformedURLException
    //   87	91	693	java/net/MalformedURLException
    //   91	95	693	java/net/MalformedURLException
    //   96	100	693	java/net/MalformedURLException
    //   107	111	693	java/net/MalformedURLException
    //   111	115	693	java/net/MalformedURLException
    //   116	120	693	java/net/MalformedURLException
    //   127	132	693	java/net/MalformedURLException
    //   132	136	693	java/net/MalformedURLException
    //   137	141	693	java/net/MalformedURLException
    //   148	153	693	java/net/MalformedURLException
    //   153	157	693	java/net/MalformedURLException
    //   158	162	693	java/net/MalformedURLException
    //   172	177	693	java/net/MalformedURLException
    //   177	181	693	java/net/MalformedURLException
    //   182	186	693	java/net/MalformedURLException
    //   187	191	693	java/net/MalformedURLException
    //   191	194	693	java/net/MalformedURLException
    //   195	199	693	java/net/MalformedURLException
    //   199	203	693	java/net/MalformedURLException
    //   208	212	693	java/net/MalformedURLException
    //   213	217	693	java/net/MalformedURLException
    //   222	226	693	java/net/MalformedURLException
    //   233	235	693	java/net/MalformedURLException
    //   237	241	693	java/net/MalformedURLException
    //   246	250	693	java/net/MalformedURLException
    //   255	258	693	java/net/MalformedURLException
    //   260	264	693	java/net/MalformedURLException
    //   269	273	693	java/net/MalformedURLException
    //   278	281	693	java/net/MalformedURLException
    //   283	287	693	java/net/MalformedURLException
    //   292	296	693	java/net/MalformedURLException
    //   301	304	693	java/net/MalformedURLException
    //   306	310	693	java/net/MalformedURLException
    //   315	319	693	java/net/MalformedURLException
    //   324	327	693	java/net/MalformedURLException
    //   329	333	693	java/net/MalformedURLException
    //   334	338	693	java/net/MalformedURLException
    //   339	343	693	java/net/MalformedURLException
    //   344	347	693	java/net/MalformedURLException
    //   348	351	693	java/net/MalformedURLException
    //   353	358	693	java/net/MalformedURLException
    //   364	369	693	java/net/MalformedURLException
    //   371	375	693	java/net/MalformedURLException
    //   379	384	693	java/net/MalformedURLException
    //   386	391	693	java/net/MalformedURLException
    //   394	399	693	java/net/MalformedURLException
    //   399	402	693	java/net/MalformedURLException
    //   403	407	693	java/net/MalformedURLException
    //   409	414	693	java/net/MalformedURLException
    //   416	421	693	java/net/MalformedURLException
    //   424	429	693	java/net/MalformedURLException
    //   429	433	693	java/net/MalformedURLException
    //   435	439	693	java/net/MalformedURLException
    //   439	443	693	java/net/MalformedURLException
    //   443	447	693	java/net/MalformedURLException
    //   448	452	693	java/net/MalformedURLException
    //   453	457	693	java/net/MalformedURLException
    //   471	474	693	java/net/MalformedURLException
    //   475	478	693	java/net/MalformedURLException
    //   480	485	693	java/net/MalformedURLException
    //   487	492	693	java/net/MalformedURLException
    //   498	503	693	java/net/MalformedURLException
    //   504	508	693	java/net/MalformedURLException
    //   510	514	693	java/net/MalformedURLException
    //   514	517	693	java/net/MalformedURLException
    //   518	521	693	java/net/MalformedURLException
    //   522	526	693	java/net/MalformedURLException
    //   528	533	693	java/net/MalformedURLException
    //   535	540	693	java/net/MalformedURLException
    //   549	554	693	java/net/MalformedURLException
    //   555	559	693	java/net/MalformedURLException
    //   559	563	693	java/net/MalformedURLException
    //   568	572	693	java/net/MalformedURLException
    //   574	579	693	java/net/MalformedURLException
    //   581	584	693	java/net/MalformedURLException
    //   586	591	693	java/net/MalformedURLException
    //   593	597	693	java/net/MalformedURLException
    //   603	608	693	java/net/MalformedURLException
    //   609	613	693	java/net/MalformedURLException
    //   616	621	693	java/net/MalformedURLException
    //   621	624	693	java/net/MalformedURLException
    //   625	628	693	java/net/MalformedURLException
    //   630	635	693	java/net/MalformedURLException
    //   635	639	693	java/net/MalformedURLException
    //   641	646	693	java/net/MalformedURLException
    //   648	653	693	java/net/MalformedURLException
    //   657	662	693	java/net/MalformedURLException
    //   670	675	693	java/net/MalformedURLException
    //   677	682	693	java/net/MalformedURLException
    //   685	690	693	java/net/MalformedURLException
    //   733	737	693	java/net/MalformedURLException
    //   764	767	693	java/net/MalformedURLException
    //   768	772	693	java/net/MalformedURLException
    //   773	777	693	java/net/MalformedURLException
    //   778	782	693	java/net/MalformedURLException
    //   784	788	693	java/net/MalformedURLException
    //   0	4	791	java/io/IOException
    //   5	8	791	java/io/IOException
    //   14	19	791	java/io/IOException
    //   20	24	791	java/io/IOException
    //   24	28	791	java/io/IOException
    //   29	33	791	java/io/IOException
    //   34	38	791	java/io/IOException
    //   39	43	791	java/io/IOException
    //   44	48	791	java/io/IOException
    //   50	54	791	java/io/IOException
    //   54	58	791	java/io/IOException
    //   59	63	791	java/io/IOException
    //   68	73	791	java/io/IOException
    //   73	77	791	java/io/IOException
    //   78	82	791	java/io/IOException
    //   87	91	791	java/io/IOException
    //   91	95	791	java/io/IOException
    //   96	100	791	java/io/IOException
    //   107	111	791	java/io/IOException
    //   111	115	791	java/io/IOException
    //   116	120	791	java/io/IOException
    //   127	132	791	java/io/IOException
    //   132	136	791	java/io/IOException
    //   137	141	791	java/io/IOException
    //   148	153	791	java/io/IOException
    //   153	157	791	java/io/IOException
    //   158	162	791	java/io/IOException
    //   172	177	791	java/io/IOException
    //   177	181	791	java/io/IOException
    //   182	186	791	java/io/IOException
    //   187	191	791	java/io/IOException
    //   191	194	791	java/io/IOException
    //   195	199	791	java/io/IOException
    //   199	203	791	java/io/IOException
    //   208	212	791	java/io/IOException
    //   213	217	791	java/io/IOException
    //   222	226	791	java/io/IOException
    //   233	235	791	java/io/IOException
    //   237	241	791	java/io/IOException
    //   246	250	791	java/io/IOException
    //   255	258	791	java/io/IOException
    //   260	264	791	java/io/IOException
    //   269	273	791	java/io/IOException
    //   278	281	791	java/io/IOException
    //   283	287	791	java/io/IOException
    //   292	296	791	java/io/IOException
    //   301	304	791	java/io/IOException
    //   306	310	791	java/io/IOException
    //   315	319	791	java/io/IOException
    //   324	327	791	java/io/IOException
    //   329	333	791	java/io/IOException
    //   334	338	791	java/io/IOException
    //   339	343	791	java/io/IOException
    //   344	347	791	java/io/IOException
    //   348	351	791	java/io/IOException
    //   353	358	791	java/io/IOException
    //   364	369	791	java/io/IOException
    //   371	375	791	java/io/IOException
    //   379	384	791	java/io/IOException
    //   386	391	791	java/io/IOException
    //   394	399	791	java/io/IOException
    //   399	402	791	java/io/IOException
    //   403	407	791	java/io/IOException
    //   409	414	791	java/io/IOException
    //   416	421	791	java/io/IOException
    //   424	429	791	java/io/IOException
    //   429	433	791	java/io/IOException
    //   435	439	791	java/io/IOException
    //   439	443	791	java/io/IOException
    //   443	447	791	java/io/IOException
    //   448	452	791	java/io/IOException
    //   453	457	791	java/io/IOException
    //   471	474	791	java/io/IOException
    //   475	478	791	java/io/IOException
    //   480	485	791	java/io/IOException
    //   487	492	791	java/io/IOException
    //   498	503	791	java/io/IOException
    //   504	508	791	java/io/IOException
    //   510	514	791	java/io/IOException
    //   514	517	791	java/io/IOException
    //   518	521	791	java/io/IOException
    //   522	526	791	java/io/IOException
    //   528	533	791	java/io/IOException
    //   535	540	791	java/io/IOException
    //   549	554	791	java/io/IOException
    //   555	559	791	java/io/IOException
    //   559	563	791	java/io/IOException
    //   568	572	791	java/io/IOException
    //   574	579	791	java/io/IOException
    //   581	584	791	java/io/IOException
    //   586	591	791	java/io/IOException
    //   593	597	791	java/io/IOException
    //   603	608	791	java/io/IOException
    //   609	613	791	java/io/IOException
    //   616	621	791	java/io/IOException
    //   621	624	791	java/io/IOException
    //   625	628	791	java/io/IOException
    //   630	635	791	java/io/IOException
    //   635	639	791	java/io/IOException
    //   641	646	791	java/io/IOException
    //   648	653	791	java/io/IOException
    //   657	662	791	java/io/IOException
    //   670	675	791	java/io/IOException
    //   677	682	791	java/io/IOException
    //   685	690	791	java/io/IOException
    //   733	737	791	java/io/IOException
    //   764	767	791	java/io/IOException
    //   768	772	791	java/io/IOException
    //   773	777	791	java/io/IOException
    //   778	782	791	java/io/IOException
    //   784	788	791	java/io/IOException
    //   0	4	823	org/json/JSONException
    //   5	8	823	org/json/JSONException
    //   14	19	823	org/json/JSONException
    //   20	24	823	org/json/JSONException
    //   24	28	823	org/json/JSONException
    //   29	33	823	org/json/JSONException
    //   34	38	823	org/json/JSONException
    //   39	43	823	org/json/JSONException
    //   44	48	823	org/json/JSONException
    //   50	54	823	org/json/JSONException
    //   54	58	823	org/json/JSONException
    //   59	63	823	org/json/JSONException
    //   68	73	823	org/json/JSONException
    //   73	77	823	org/json/JSONException
    //   78	82	823	org/json/JSONException
    //   87	91	823	org/json/JSONException
    //   91	95	823	org/json/JSONException
    //   96	100	823	org/json/JSONException
    //   107	111	823	org/json/JSONException
    //   111	115	823	org/json/JSONException
    //   116	120	823	org/json/JSONException
    //   127	132	823	org/json/JSONException
    //   132	136	823	org/json/JSONException
    //   137	141	823	org/json/JSONException
    //   148	153	823	org/json/JSONException
    //   153	157	823	org/json/JSONException
    //   158	162	823	org/json/JSONException
    //   172	177	823	org/json/JSONException
    //   177	181	823	org/json/JSONException
    //   182	186	823	org/json/JSONException
    //   187	191	823	org/json/JSONException
    //   191	194	823	org/json/JSONException
    //   195	199	823	org/json/JSONException
    //   199	203	823	org/json/JSONException
    //   208	212	823	org/json/JSONException
    //   213	217	823	org/json/JSONException
    //   222	226	823	org/json/JSONException
    //   233	235	823	org/json/JSONException
    //   237	241	823	org/json/JSONException
    //   246	250	823	org/json/JSONException
    //   255	258	823	org/json/JSONException
    //   260	264	823	org/json/JSONException
    //   269	273	823	org/json/JSONException
    //   278	281	823	org/json/JSONException
    //   283	287	823	org/json/JSONException
    //   292	296	823	org/json/JSONException
    //   301	304	823	org/json/JSONException
    //   306	310	823	org/json/JSONException
    //   315	319	823	org/json/JSONException
    //   324	327	823	org/json/JSONException
    //   329	333	823	org/json/JSONException
    //   334	338	823	org/json/JSONException
    //   339	343	823	org/json/JSONException
    //   344	347	823	org/json/JSONException
    //   348	351	823	org/json/JSONException
    //   353	358	823	org/json/JSONException
    //   364	369	823	org/json/JSONException
    //   371	375	823	org/json/JSONException
    //   379	384	823	org/json/JSONException
    //   386	391	823	org/json/JSONException
    //   394	399	823	org/json/JSONException
    //   399	402	823	org/json/JSONException
    //   403	407	823	org/json/JSONException
    //   409	414	823	org/json/JSONException
    //   416	421	823	org/json/JSONException
    //   424	429	823	org/json/JSONException
    //   429	433	823	org/json/JSONException
    //   435	439	823	org/json/JSONException
    //   439	443	823	org/json/JSONException
    //   443	447	823	org/json/JSONException
    //   448	452	823	org/json/JSONException
    //   453	457	823	org/json/JSONException
    //   471	474	823	org/json/JSONException
    //   475	478	823	org/json/JSONException
    //   480	485	823	org/json/JSONException
    //   487	492	823	org/json/JSONException
    //   498	503	823	org/json/JSONException
    //   504	508	823	org/json/JSONException
    //   510	514	823	org/json/JSONException
    //   514	517	823	org/json/JSONException
    //   518	521	823	org/json/JSONException
    //   522	526	823	org/json/JSONException
    //   528	533	823	org/json/JSONException
    //   535	540	823	org/json/JSONException
    //   549	554	823	org/json/JSONException
    //   555	559	823	org/json/JSONException
    //   559	563	823	org/json/JSONException
    //   568	572	823	org/json/JSONException
    //   574	579	823	org/json/JSONException
    //   581	584	823	org/json/JSONException
    //   586	591	823	org/json/JSONException
    //   593	597	823	org/json/JSONException
    //   603	608	823	org/json/JSONException
    //   609	613	823	org/json/JSONException
    //   616	621	823	org/json/JSONException
    //   621	624	823	org/json/JSONException
    //   625	628	823	org/json/JSONException
    //   630	635	823	org/json/JSONException
    //   635	639	823	org/json/JSONException
    //   641	646	823	org/json/JSONException
    //   648	653	823	org/json/JSONException
    //   657	662	823	org/json/JSONException
    //   670	675	823	org/json/JSONException
    //   677	682	823	org/json/JSONException
    //   685	690	823	org/json/JSONException
    //   733	737	823	org/json/JSONException
    //   764	767	823	org/json/JSONException
    //   768	772	823	org/json/JSONException
    //   773	777	823	org/json/JSONException
    //   778	782	823	org/json/JSONException
    //   784	788	823	org/json/JSONException
    //   0	4	855	finally
    //   5	8	855	finally
    //   14	19	855	finally
    //   20	24	855	finally
    //   24	28	855	finally
    //   29	33	855	finally
    //   34	38	855	finally
    //   39	43	855	finally
    //   44	48	855	finally
    //   50	54	855	finally
    //   54	58	855	finally
    //   59	63	855	finally
    //   68	73	855	finally
    //   73	77	855	finally
    //   78	82	855	finally
    //   87	91	855	finally
    //   91	95	855	finally
    //   96	100	855	finally
    //   107	111	855	finally
    //   111	115	855	finally
    //   116	120	855	finally
    //   127	132	855	finally
    //   132	136	855	finally
    //   137	141	855	finally
    //   148	153	855	finally
    //   153	157	855	finally
    //   158	162	855	finally
    //   172	177	855	finally
    //   177	181	855	finally
    //   182	186	855	finally
    //   187	191	855	finally
    //   191	194	855	finally
    //   195	199	855	finally
    //   199	203	855	finally
    //   208	212	855	finally
    //   213	217	855	finally
    //   222	226	855	finally
    //   233	235	855	finally
    //   237	241	855	finally
    //   246	250	855	finally
    //   255	258	855	finally
    //   260	264	855	finally
    //   269	273	855	finally
    //   278	281	855	finally
    //   283	287	855	finally
    //   292	296	855	finally
    //   301	304	855	finally
    //   306	310	855	finally
    //   315	319	855	finally
    //   324	327	855	finally
    //   329	333	855	finally
    //   334	338	855	finally
    //   339	343	855	finally
    //   344	347	855	finally
    //   348	351	855	finally
    //   353	358	855	finally
    //   364	369	855	finally
    //   371	375	855	finally
    //   379	384	855	finally
    //   386	391	855	finally
    //   394	399	855	finally
    //   399	402	855	finally
    //   403	407	855	finally
    //   409	414	855	finally
    //   416	421	855	finally
    //   424	429	855	finally
    //   429	433	855	finally
    //   435	439	855	finally
    //   439	443	855	finally
    //   443	447	855	finally
    //   448	452	855	finally
    //   453	457	855	finally
    //   471	474	855	finally
    //   475	478	855	finally
    //   480	485	855	finally
    //   487	492	855	finally
    //   498	503	855	finally
    //   504	508	855	finally
    //   510	514	855	finally
    //   514	517	855	finally
    //   518	521	855	finally
    //   522	526	855	finally
    //   528	533	855	finally
    //   535	540	855	finally
    //   549	554	855	finally
    //   555	559	855	finally
    //   559	563	855	finally
    //   568	572	855	finally
    //   574	579	855	finally
    //   581	584	855	finally
    //   586	591	855	finally
    //   593	597	855	finally
    //   603	608	855	finally
    //   609	613	855	finally
    //   616	621	855	finally
    //   621	624	855	finally
    //   625	628	855	finally
    //   630	635	855	finally
    //   635	639	855	finally
    //   641	646	855	finally
    //   648	653	855	finally
    //   657	662	855	finally
    //   670	675	855	finally
    //   677	682	855	finally
    //   685	690	855	finally
    //   694	698	855	finally
    //   733	737	855	finally
    //   764	767	855	finally
    //   768	772	855	finally
    //   773	777	855	finally
    //   778	782	855	finally
    //   784	788	855	finally
    //   792	796	855	finally
    //   824	828	855	finally
  }
  
  protected void a(String paramString)
  {
    int i = 1;
    super.onPostExecute(paramString);
    Object localObject1 = b;
    Object localObject2 = z.a(paramString);
    h = ((List)localObject2);
    localObject1 = b.h;
    boolean bool = ((List)localObject1).isEmpty();
    if (bool)
    {
      localObject1 = b.getApplicationContext();
      localObject2 = "No match found";
      localObject1 = Toast.makeText((Context)localObject1, (CharSequence)localObject2, i);
      ((Toast)localObject1).show();
    }
    localObject1 = b.h;
    int j = ((List)localObject1).size();
    int k = 100;
    if (j >= k)
    {
      b.b();
      localObject1 = b.getApplicationContext();
      localObject2 = "Only the top 100 results are being displayed. Please be more specific. ";
      localObject1 = Toast.makeText((Context)localObject1, (CharSequence)localObject2, i);
      ((Toast)localObject1).show();
    }
    for (;;)
    {
      b.g.remove(this);
      localObject1 = b.g;
      j = ((List)localObject1).size();
      if (j == 0)
      {
        localObject1 = b.f;
        k = 4;
        ((ProgressBar)localObject1).setVisibility(k);
      }
      return;
      localObject1 = b;
      ((AdvancedListFive)localObject1).b();
    }
  }
  
  protected void onPreExecute()
  {
    super.onPreExecute();
    Object localObject = b.g;
    int i = ((List)localObject).size();
    if (i == 0)
    {
      localObject = b.f;
      ((ProgressBar)localObject).setVisibility(0);
    }
    b.g.add(this);
  }
}

/* Location:
 * Qualified Name:     in.gov.hp.Aadhaar_HP.SRDH.b
 * Java Class Version: 5 (49.0)
 * JD-Core Version:    0.7.1
 */