package in.gov.hp.Aadhaar_HP.SRDH;

public class l
{
  /* Error */
  public static String a(String paramString)
  {
    // Byte code:
    //   0: new 6	java/net/URL
    //   3: astore_1
    //   4: aload_1
    //   5: aload_0
    //   6: invokespecial 10	java/net/URL:<init>	(Ljava/lang/String;)V
    //   9: aload_1
    //   10: invokevirtual 14	java/net/URL:openConnection	()Ljava/net/URLConnection;
    //   13: astore_1
    //   14: aload_1
    //   15: checkcast 16	java/net/HttpURLConnection
    //   18: astore_1
    //   19: new 18	java/lang/StringBuilder
    //   22: astore_2
    //   23: aload_2
    //   24: invokespecial 21	java/lang/StringBuilder:<init>	()V
    //   27: new 23	java/io/BufferedReader
    //   30: astore_3
    //   31: new 25	java/io/InputStreamReader
    //   34: astore 4
    //   36: aload_1
    //   37: invokevirtual 29	java/net/HttpURLConnection:getInputStream	()Ljava/io/InputStream;
    //   40: astore_1
    //   41: aload 4
    //   43: aload_1
    //   44: invokespecial 32	java/io/InputStreamReader:<init>	(Ljava/io/InputStream;)V
    //   47: aload_3
    //   48: aload 4
    //   50: invokespecial 35	java/io/BufferedReader:<init>	(Ljava/io/Reader;)V
    //   53: aload_3
    //   54: invokevirtual 39	java/io/BufferedReader:readLine	()Ljava/lang/String;
    //   57: astore_1
    //   58: aload_1
    //   59: ifnull +62 -> 121
    //   62: new 18	java/lang/StringBuilder
    //   65: astore 4
    //   67: aload 4
    //   69: invokespecial 21	java/lang/StringBuilder:<init>	()V
    //   72: aload 4
    //   74: aload_1
    //   75: invokevirtual 43	java/lang/StringBuilder:append	(Ljava/lang/String;)Ljava/lang/StringBuilder;
    //   78: astore_1
    //   79: ldc 45
    //   81: astore 4
    //   83: aload_1
    //   84: aload 4
    //   86: invokevirtual 43	java/lang/StringBuilder:append	(Ljava/lang/String;)Ljava/lang/StringBuilder;
    //   89: astore_1
    //   90: aload_1
    //   91: invokevirtual 48	java/lang/StringBuilder:toString	()Ljava/lang/String;
    //   94: astore_1
    //   95: aload_2
    //   96: aload_1
    //   97: invokevirtual 43	java/lang/StringBuilder:append	(Ljava/lang/String;)Ljava/lang/StringBuilder;
    //   100: pop
    //   101: goto -48 -> 53
    //   104: astore_1
    //   105: aload_1
    //   106: invokevirtual 53	java/lang/Exception:printStackTrace	()V
    //   109: aload_3
    //   110: ifnull +7 -> 117
    //   113: aload_3
    //   114: invokevirtual 56	java/io/BufferedReader:close	()V
    //   117: aconst_null
    //   118: astore_1
    //   119: aload_1
    //   120: areturn
    //   121: aload_2
    //   122: invokevirtual 48	java/lang/StringBuilder:toString	()Ljava/lang/String;
    //   125: astore_1
    //   126: aload_3
    //   127: ifnull -8 -> 119
    //   130: aload_3
    //   131: invokevirtual 56	java/io/BufferedReader:close	()V
    //   134: goto -15 -> 119
    //   137: invokevirtual 59	java/io/IOException:printStackTrace	()V
    //   140: aconst_null
    //   141: astore_1
    //   142: goto -23 -> 119
    //   145: invokevirtual 59	java/io/IOException:printStackTrace	()V
    //   148: aconst_null
    //   149: astore_1
    //   150: goto -31 -> 119
    //   153: astore_1
    //   154: aconst_null
    //   155: astore_3
    //   156: aload_3
    //   157: ifnull +7 -> 164
    //   160: aload_3
    //   161: invokevirtual 56	java/io/BufferedReader:close	()V
    //   164: aload_1
    //   165: athrow
    //   166: invokevirtual 59	java/io/IOException:printStackTrace	()V
    //   169: aconst_null
    //   170: astore_1
    //   171: goto -52 -> 119
    //   174: astore_1
    //   175: goto -19 -> 156
    //   178: astore_1
    //   179: aconst_null
    //   180: astore_3
    //   181: goto -76 -> 105
    // Local variable table:
    //   start	length	slot	name	signature
    //   0	184	0	paramString	String
    //   3	94	1	localObject1	Object
    //   104	2	1	localException1	Exception
    //   118	32	1	str	String
    //   153	12	1	localObject2	Object
    //   170	1	1	localObject3	Object
    //   174	1	1	localObject4	Object
    //   178	1	1	localException2	Exception
    //   22	100	2	localStringBuilder	StringBuilder
    //   30	151	3	localBufferedReader	java.io.BufferedReader
    //   34	51	4	localObject5	Object
    //   137	1	11	localIOException1	java.io.IOException
    //   145	1	12	localIOException2	java.io.IOException
    //   166	1	13	localIOException3	java.io.IOException
    // Exception table:
    //   from	to	target	type
    //   53	57	104	java/lang/Exception
    //   62	65	104	java/lang/Exception
    //   67	72	104	java/lang/Exception
    //   74	78	104	java/lang/Exception
    //   84	89	104	java/lang/Exception
    //   90	94	104	java/lang/Exception
    //   96	101	104	java/lang/Exception
    //   121	125	104	java/lang/Exception
    //   130	134	137	java/io/IOException
    //   113	117	145	java/io/IOException
    //   0	3	153	finally
    //   5	9	153	finally
    //   9	13	153	finally
    //   14	18	153	finally
    //   19	22	153	finally
    //   23	27	153	finally
    //   27	30	153	finally
    //   31	34	153	finally
    //   36	40	153	finally
    //   43	47	153	finally
    //   48	53	153	finally
    //   160	164	166	java/io/IOException
    //   53	57	174	finally
    //   62	65	174	finally
    //   67	72	174	finally
    //   74	78	174	finally
    //   84	89	174	finally
    //   90	94	174	finally
    //   96	101	174	finally
    //   105	109	174	finally
    //   121	125	174	finally
    //   0	3	178	java/lang/Exception
    //   5	9	178	java/lang/Exception
    //   9	13	178	java/lang/Exception
    //   14	18	178	java/lang/Exception
    //   19	22	178	java/lang/Exception
    //   23	27	178	java/lang/Exception
    //   27	30	178	java/lang/Exception
    //   31	34	178	java/lang/Exception
    //   36	40	178	java/lang/Exception
    //   43	47	178	java/lang/Exception
    //   48	53	178	java/lang/Exception
  }
}

/* Location:
 * Qualified Name:     in.gov.hp.Aadhaar_HP.SRDH.l
 * Java Class Version: 5 (49.0)
 * JD-Core Version:    0.7.1
 */