package in.gov.mgov.jh.uid;

import android.app.Dialog;
import android.app.ProgressDialog;
import android.os.AsyncTask;
import android.view.View;
import android.view.View.OnClickListener;
import android.widget.Button;
import android.widget.TextView;
import android.widget.Toast;

class HomeFragment$SendSMSInternet
  extends AsyncTask<String, String, String>
{
  ProgressDialog pd = null;
  
  HomeFragment$SendSMSInternet(HomeFragment paramHomeFragment) {}
  
  /* Error */
  protected String doInBackground(String... paramVarArgs)
  {
    // Byte code:
    //   0: aconst_null
    //   1: astore 4
    //   3: aconst_null
    //   4: astore 5
    //   6: aconst_null
    //   7: astore_3
    //   8: aload_1
    //   9: iconst_0
    //   10: aaload
    //   11: astore 6
    //   13: aload_1
    //   14: iconst_1
    //   15: aaload
    //   16: astore 7
    //   18: aload 5
    //   20: astore_1
    //   21: new 37	java/net/URL
    //   24: dup
    //   25: ldc 39
    //   27: invokespecial 42	java/net/URL:<init>	(Ljava/lang/String;)V
    //   30: invokevirtual 46	java/net/URL:openConnection	()Ljava/net/URLConnection;
    //   33: checkcast 48	java/net/HttpURLConnection
    //   36: astore 5
    //   38: aload 5
    //   40: astore_3
    //   41: aload 5
    //   43: astore 4
    //   45: aload 5
    //   47: astore_1
    //   48: aload 5
    //   50: iconst_1
    //   51: invokevirtual 52	java/net/HttpURLConnection:setDoOutput	(Z)V
    //   54: aload 5
    //   56: astore_3
    //   57: aload 5
    //   59: astore 4
    //   61: aload 5
    //   63: astore_1
    //   64: aload 5
    //   66: iconst_0
    //   67: invokevirtual 56	java/net/HttpURLConnection:setChunkedStreamingMode	(I)V
    //   70: aload 5
    //   72: astore_3
    //   73: aload 5
    //   75: astore 4
    //   77: aload 5
    //   79: astore_1
    //   80: aload 5
    //   82: iconst_0
    //   83: invokevirtual 59	java/net/HttpURLConnection:setInstanceFollowRedirects	(Z)V
    //   86: aload 5
    //   88: astore_3
    //   89: aload 5
    //   91: astore 4
    //   93: aload 5
    //   95: astore_1
    //   96: aload 5
    //   98: ldc 61
    //   100: invokevirtual 64	java/net/HttpURLConnection:setRequestMethod	(Ljava/lang/String;)V
    //   103: aload 5
    //   105: astore_3
    //   106: aload 5
    //   108: astore 4
    //   110: aload 5
    //   112: astore_1
    //   113: new 66	java/util/LinkedHashMap
    //   116: dup
    //   117: invokespecial 67	java/util/LinkedHashMap:<init>	()V
    //   120: astore 8
    //   122: aload 5
    //   124: astore_3
    //   125: aload 5
    //   127: astore 4
    //   129: aload 5
    //   131: astore_1
    //   132: aload 8
    //   134: ldc 69
    //   136: ldc 71
    //   138: invokeinterface 77 3 0
    //   143: pop
    //   144: aload 5
    //   146: astore_3
    //   147: aload 5
    //   149: astore 4
    //   151: aload 5
    //   153: astore_1
    //   154: aload 8
    //   156: ldc 79
    //   158: ldc 81
    //   160: invokeinterface 77 3 0
    //   165: pop
    //   166: aload 5
    //   168: astore_3
    //   169: aload 5
    //   171: astore 4
    //   173: aload 5
    //   175: astore_1
    //   176: aload 8
    //   178: ldc 83
    //   180: aload 6
    //   182: invokeinterface 77 3 0
    //   187: pop
    //   188: aload 5
    //   190: astore_3
    //   191: aload 5
    //   193: astore 4
    //   195: aload 5
    //   197: astore_1
    //   198: aload 8
    //   200: ldc 85
    //   202: aload 7
    //   204: invokeinterface 77 3 0
    //   209: pop
    //   210: aload 5
    //   212: astore_3
    //   213: aload 5
    //   215: astore 4
    //   217: aload 5
    //   219: astore_1
    //   220: aload 8
    //   222: ldc 87
    //   224: ldc 89
    //   226: invokeinterface 77 3 0
    //   231: pop
    //   232: aload 5
    //   234: astore_3
    //   235: aload 5
    //   237: astore 4
    //   239: aload 5
    //   241: astore_1
    //   242: aload 8
    //   244: ldc 91
    //   246: ldc 89
    //   248: invokeinterface 77 3 0
    //   253: pop
    //   254: aload 5
    //   256: astore_3
    //   257: aload 5
    //   259: astore 4
    //   261: aload 5
    //   263: astore_1
    //   264: new 93	java/lang/StringBuilder
    //   267: dup
    //   268: invokespecial 94	java/lang/StringBuilder:<init>	()V
    //   271: astore 6
    //   273: aload 5
    //   275: astore_3
    //   276: aload 5
    //   278: astore 4
    //   280: aload 5
    //   282: astore_1
    //   283: aload 8
    //   285: invokeinterface 98 1 0
    //   290: invokeinterface 104 1 0
    //   295: astore 7
    //   297: aload 5
    //   299: astore_3
    //   300: aload 5
    //   302: astore 4
    //   304: aload 5
    //   306: astore_1
    //   307: aload 7
    //   309: invokeinterface 110 1 0
    //   314: ifeq +159 -> 473
    //   317: aload 5
    //   319: astore_3
    //   320: aload 5
    //   322: astore 4
    //   324: aload 5
    //   326: astore_1
    //   327: aload 7
    //   329: invokeinterface 114 1 0
    //   334: checkcast 116	java/util/Map$Entry
    //   337: astore 8
    //   339: aload 5
    //   341: astore_3
    //   342: aload 5
    //   344: astore 4
    //   346: aload 5
    //   348: astore_1
    //   349: aload 6
    //   351: invokevirtual 120	java/lang/StringBuilder:length	()I
    //   354: ifeq +21 -> 375
    //   357: aload 5
    //   359: astore_3
    //   360: aload 5
    //   362: astore 4
    //   364: aload 5
    //   366: astore_1
    //   367: aload 6
    //   369: bipush 38
    //   371: invokevirtual 124	java/lang/StringBuilder:append	(C)Ljava/lang/StringBuilder;
    //   374: pop
    //   375: aload 5
    //   377: astore_3
    //   378: aload 5
    //   380: astore 4
    //   382: aload 5
    //   384: astore_1
    //   385: aload 6
    //   387: aload 8
    //   389: invokeinterface 127 1 0
    //   394: checkcast 129	java/lang/String
    //   397: ldc -125
    //   399: invokestatic 137	java/net/URLEncoder:encode	(Ljava/lang/String;Ljava/lang/String;)Ljava/lang/String;
    //   402: invokevirtual 140	java/lang/StringBuilder:append	(Ljava/lang/String;)Ljava/lang/StringBuilder;
    //   405: pop
    //   406: aload 5
    //   408: astore_3
    //   409: aload 5
    //   411: astore 4
    //   413: aload 5
    //   415: astore_1
    //   416: aload 6
    //   418: bipush 61
    //   420: invokevirtual 124	java/lang/StringBuilder:append	(C)Ljava/lang/StringBuilder;
    //   423: pop
    //   424: aload 5
    //   426: astore_3
    //   427: aload 5
    //   429: astore 4
    //   431: aload 5
    //   433: astore_1
    //   434: aload 6
    //   436: aload 8
    //   438: invokeinterface 143 1 0
    //   443: invokestatic 147	java/lang/String:valueOf	(Ljava/lang/Object;)Ljava/lang/String;
    //   446: ldc -125
    //   448: invokestatic 137	java/net/URLEncoder:encode	(Ljava/lang/String;Ljava/lang/String;)Ljava/lang/String;
    //   451: invokevirtual 140	java/lang/StringBuilder:append	(Ljava/lang/String;)Ljava/lang/StringBuilder;
    //   454: pop
    //   455: goto -158 -> 297
    //   458: astore 4
    //   460: aload_3
    //   461: astore_1
    //   462: aload 4
    //   464: invokevirtual 150	java/net/MalformedURLException:printStackTrace	()V
    //   467: aload_3
    //   468: invokevirtual 153	java/net/HttpURLConnection:disconnect	()V
    //   471: aconst_null
    //   472: areturn
    //   473: aload 5
    //   475: astore_3
    //   476: aload 5
    //   478: astore 4
    //   480: aload 5
    //   482: astore_1
    //   483: aload 6
    //   485: invokevirtual 157	java/lang/StringBuilder:toString	()Ljava/lang/String;
    //   488: ldc -125
    //   490: invokevirtual 161	java/lang/String:getBytes	(Ljava/lang/String;)[B
    //   493: astore 6
    //   495: aload 5
    //   497: astore_3
    //   498: aload 5
    //   500: astore 4
    //   502: aload 5
    //   504: astore_1
    //   505: aload 6
    //   507: arraylength
    //   508: istore_2
    //   509: aload 5
    //   511: astore_3
    //   512: aload 5
    //   514: astore 4
    //   516: aload 5
    //   518: astore_1
    //   519: aload 5
    //   521: ldc -93
    //   523: ldc -91
    //   525: invokevirtual 169	java/net/HttpURLConnection:setRequestProperty	(Ljava/lang/String;Ljava/lang/String;)V
    //   528: aload 5
    //   530: astore_3
    //   531: aload 5
    //   533: astore 4
    //   535: aload 5
    //   537: astore_1
    //   538: aload 5
    //   540: ldc -85
    //   542: iload_2
    //   543: invokestatic 176	java/lang/Integer:toString	(I)Ljava/lang/String;
    //   546: invokevirtual 169	java/net/HttpURLConnection:setRequestProperty	(Ljava/lang/String;Ljava/lang/String;)V
    //   549: aload 5
    //   551: astore_3
    //   552: aload 5
    //   554: astore 4
    //   556: aload 5
    //   558: astore_1
    //   559: aload 5
    //   561: iconst_0
    //   562: invokevirtual 179	java/net/HttpURLConnection:setUseCaches	(Z)V
    //   565: aload 5
    //   567: astore_3
    //   568: aload 5
    //   570: astore 4
    //   572: aload 5
    //   574: astore_1
    //   575: aload 5
    //   577: invokevirtual 183	java/net/HttpURLConnection:getOutputStream	()Ljava/io/OutputStream;
    //   580: aload 6
    //   582: invokevirtual 189	java/io/OutputStream:write	([B)V
    //   585: aload 5
    //   587: astore_3
    //   588: aload 5
    //   590: astore 4
    //   592: aload 5
    //   594: astore_1
    //   595: new 191	java/io/BufferedReader
    //   598: dup
    //   599: new 193	java/io/InputStreamReader
    //   602: dup
    //   603: new 195	java/io/BufferedInputStream
    //   606: dup
    //   607: aload 5
    //   609: invokevirtual 199	java/net/HttpURLConnection:getInputStream	()Ljava/io/InputStream;
    //   612: invokespecial 202	java/io/BufferedInputStream:<init>	(Ljava/io/InputStream;)V
    //   615: invokespecial 203	java/io/InputStreamReader:<init>	(Ljava/io/InputStream;)V
    //   618: invokespecial 206	java/io/BufferedReader:<init>	(Ljava/io/Reader;)V
    //   621: invokevirtual 209	java/io/BufferedReader:readLine	()Ljava/lang/String;
    //   624: astore 6
    //   626: aload 5
    //   628: invokevirtual 153	java/net/HttpURLConnection:disconnect	()V
    //   631: aload 6
    //   633: areturn
    //   634: astore_3
    //   635: aload 4
    //   637: astore_1
    //   638: aload_3
    //   639: invokevirtual 210	java/io/IOException:printStackTrace	()V
    //   642: aload 4
    //   644: invokevirtual 153	java/net/HttpURLConnection:disconnect	()V
    //   647: aconst_null
    //   648: areturn
    //   649: astore_3
    //   650: aload_1
    //   651: invokevirtual 153	java/net/HttpURLConnection:disconnect	()V
    //   654: aload_3
    //   655: athrow
    // Local variable table:
    //   start	length	slot	name	signature
    //   0	656	0	this	SendSMSInternet
    //   0	656	1	paramVarArgs	String[]
    //   508	35	2	i	int
    //   7	581	3	localHttpURLConnection1	java.net.HttpURLConnection
    //   634	5	3	localIOException	java.io.IOException
    //   649	6	3	localObject1	Object
    //   1	429	4	localObject2	Object
    //   458	5	4	localMalformedURLException	java.net.MalformedURLException
    //   478	165	4	localObject3	Object
    //   4	623	5	localHttpURLConnection2	java.net.HttpURLConnection
    //   11	621	6	localObject4	Object
    //   16	312	7	localObject5	Object
    //   120	317	8	localObject6	Object
    // Exception table:
    //   from	to	target	type
    //   21	38	458	java/net/MalformedURLException
    //   48	54	458	java/net/MalformedURLException
    //   64	70	458	java/net/MalformedURLException
    //   80	86	458	java/net/MalformedURLException
    //   96	103	458	java/net/MalformedURLException
    //   113	122	458	java/net/MalformedURLException
    //   132	144	458	java/net/MalformedURLException
    //   154	166	458	java/net/MalformedURLException
    //   176	188	458	java/net/MalformedURLException
    //   198	210	458	java/net/MalformedURLException
    //   220	232	458	java/net/MalformedURLException
    //   242	254	458	java/net/MalformedURLException
    //   264	273	458	java/net/MalformedURLException
    //   283	297	458	java/net/MalformedURLException
    //   307	317	458	java/net/MalformedURLException
    //   327	339	458	java/net/MalformedURLException
    //   349	357	458	java/net/MalformedURLException
    //   367	375	458	java/net/MalformedURLException
    //   385	406	458	java/net/MalformedURLException
    //   416	424	458	java/net/MalformedURLException
    //   434	455	458	java/net/MalformedURLException
    //   483	495	458	java/net/MalformedURLException
    //   505	509	458	java/net/MalformedURLException
    //   519	528	458	java/net/MalformedURLException
    //   538	549	458	java/net/MalformedURLException
    //   559	565	458	java/net/MalformedURLException
    //   575	585	458	java/net/MalformedURLException
    //   595	626	458	java/net/MalformedURLException
    //   21	38	634	java/io/IOException
    //   48	54	634	java/io/IOException
    //   64	70	634	java/io/IOException
    //   80	86	634	java/io/IOException
    //   96	103	634	java/io/IOException
    //   113	122	634	java/io/IOException
    //   132	144	634	java/io/IOException
    //   154	166	634	java/io/IOException
    //   176	188	634	java/io/IOException
    //   198	210	634	java/io/IOException
    //   220	232	634	java/io/IOException
    //   242	254	634	java/io/IOException
    //   264	273	634	java/io/IOException
    //   283	297	634	java/io/IOException
    //   307	317	634	java/io/IOException
    //   327	339	634	java/io/IOException
    //   349	357	634	java/io/IOException
    //   367	375	634	java/io/IOException
    //   385	406	634	java/io/IOException
    //   416	424	634	java/io/IOException
    //   434	455	634	java/io/IOException
    //   483	495	634	java/io/IOException
    //   505	509	634	java/io/IOException
    //   519	528	634	java/io/IOException
    //   538	549	634	java/io/IOException
    //   559	565	634	java/io/IOException
    //   575	585	634	java/io/IOException
    //   595	626	634	java/io/IOException
    //   21	38	649	finally
    //   48	54	649	finally
    //   64	70	649	finally
    //   80	86	649	finally
    //   96	103	649	finally
    //   113	122	649	finally
    //   132	144	649	finally
    //   154	166	649	finally
    //   176	188	649	finally
    //   198	210	649	finally
    //   220	232	649	finally
    //   242	254	649	finally
    //   264	273	649	finally
    //   283	297	649	finally
    //   307	317	649	finally
    //   327	339	649	finally
    //   349	357	649	finally
    //   367	375	649	finally
    //   385	406	649	finally
    //   416	424	649	finally
    //   434	455	649	finally
    //   462	467	649	finally
    //   483	495	649	finally
    //   505	509	649	finally
    //   519	528	649	finally
    //   538	549	649	finally
    //   559	565	649	finally
    //   575	585	649	finally
    //   595	626	649	finally
    //   638	642	649	finally
  }
  
  protected void onPostExecute(String paramString)
  {
    super.onPostExecute(paramString);
    pd.dismiss();
    Toast.makeText(this$0.getActivity(), paramString, 1).show();
    final Dialog localDialog = new Dialog(this$0.getActivity());
    localDialog.setTitle("Response From Pull Service");
    localDialog.setContentView(2130968629);
    Button localButton = (Button)localDialog.findViewById(2131492987);
    ((TextView)localDialog.findViewById(2131492972)).setText(paramString);
    localDialog.show();
    localButton.setOnClickListener(new View.OnClickListener()
    {
      public void onClick(View paramAnonymousView)
      {
        localDialog.dismiss();
      }
    });
  }
  
  protected void onPreExecute()
  {
    super.onPreExecute();
    pd = new ProgressDialog(this$0.getActivity());
    pd.setTitle("loading...");
    pd.setProgressStyle(0);
    pd.show();
  }
}

/* Location:
 * Qualified Name:     in.gov.mgov.jh.uid.HomeFragment.SendSMSInternet
 * Java Class Version: 6 (50.0)
 * JD-Core Version:    0.7.1
 */